tahoma_gpt/__init__.py
tahoma_gpt/__version__.py
tahoma_gpt/__version__.py~
tahoma_gpt/tahoma_gpt.py
tahoma_gpt/test/__init__.py
tahoma_gpt/test/test.py
tahoma_gpt-0.0.8.dist-info/LICENSE
tahoma_gpt-0.0.8.dist-info/METADATA
tahoma_gpt-0.0.8.dist-info/WHEEL
tahoma_gpt-0.0.8.dist-info/entry_points.txt
tahoma_gpt-0.0.8.dist-info/top_level.txt
tahoma_gpt-0.0.8.dist-info/RECORD
