Metadata-Version: 2.1
Name: tahoma-gpt
Version: 0.0.8
Summary: This is a very easy API for controlling Somfy Tahoma's devices written in Python3, thanks to the pyoverkiz API. You just need a three-word input to control a device
Author-email: Pzim-devdata <contact@pzim.fr>
Project-URL: Homepage, https://github.com/pzim-devdata/tahoma-gpt
Project-URL: Bug Tracker, https://github.com/pzim-devdata/tahoma-gpt/issues
Keywords: tahoma_gpt,somfy,api
Classifier: Programming Language :: Python :: 3
Classifier: License :: OSI Approved :: MIT License
Classifier: Operating System :: OS Independent
Requires-Python: >=3.7
License-File: LICENSE
Requires-Dist: openai (>=0.27.8)
Requires-Dist: inputimeout (>=1.0.4)
